[{"id":0,"parent":17,"joint":"hinge","name":"lever","parts":[{"id":40,"name":"lever","children":[]}],"jointData":{"axis":{"origin":[-0.01638226315379143,-0.3087243074279856,0],"direction":[0,0,1]},"limit":{"a":0,"b":15.479999999999999,"noLimit":false}}},{"id":1,"parent":17,"joint":"hinge","name":"knob","parts":[{"id":41,"name":"knob","children":[]}],"jointData":{"axis":{"origin":[-0.004240464824702992,0.03404987679122426,0.19300801038325405],"direction":[-0.000057221703244016534,0.9847923906468601,-0.17373527002229266]},"limit":{"a":0,"b":0,"noLimit":true}}},{"id":2,"parent":18,"joint":"hinge","name":"caster_yoke","parts":[{"id":37,"name":"caster_yoke","children":[]}],"jointData":{"axis":{"origin":[-0.4109760163604021,0,0.029821438934100997],"direction":[0,1,0]},"limit":{"a":0,"b":0,"noLimit":true}}},{"id":3,"parent":2,"joint":"hinge","name":"wheel","parts":[{"id":38,"name":"wheel","children":[]}],"jointData":{"axis":{"origin":[0,-0.8117528426753511,-0.004365204991788402],"direction":[-1,0,0]},"limit":{"a":0,"b":0,"noLimit":true}}},{"id":4,"parent":2,"joint":"hinge","name":"wheel","parts":[{"id":39,"name":"wheel","children":[]}],"jointData":{"axis":{"origin":[0,-0.8117528426753511,-0.004365204991788402],"direction":[-1,0,0]},"limit":{"a":0,"b":0,"noLimit":true}}},{"id":5,"parent":18,"joint":"hinge","name":"caster_yoke","parts":[{"id":34,"name":"caster_yoke","children":[]}],"jointData":{"axis":{"origin":[0.003734983786463737,0,-0.2695848207415639],"direction":[0,1,0]},"limit":{"a":0,"b":0,"noLimit":true}}},{"id":6,"parent":5,"joint":"hinge","name":"wheel","parts":[{"id":35,"name":"wheel","children":[]}],"jointData":{"axis":{"origin":[0,-0.8098480609708484,-0.3003343854576705],"direction":[-1,0,0]},"limit":{"a":0,"b":0,"noLimit":true}}},{"id":7,"parent":5,"joint":"hinge","name":"wheel","parts":[{"id":36,"name":"wheel","children":[]}],"jointData":{"axis":{"origin":[0,-0.8098480609708484,-0.3003343854576705],"direction":[-1,0,0]},"limit":{"a":0,"b":0,"noLimit":true}}},{"id":8,"parent":18,"joint":"hinge","name":"caster_yoke","parts":[{"id":31,"name":"caster_yoke","children":[]}],"jointData":{"axis":{"origin":[0.4150677405015231,0,0.02713694508942962],"direction":[0,1,0]},"limit":{"a":0,"b":0,"noLimit":true}}},{"id":9,"parent":8,"joint":"hinge","name":"wheel","parts":[{"id":32,"name":"wheel","children":[]}],"jointData":{"axis":{"origin":[0,-0.8098479390291516,-0.0037316145423295696],"direction":[-1,0,0]},"limit":{"a":0,"b":0,"noLimit":true}}},{"id":10,"parent":8,"joint":"hinge","name":"wheel","parts":[{"id":33,"name":"wheel","children":[]}],"jointData":{"axis":{"origin":[0,-0.8098479390291516,-0.0037316145423295696],"direction":[-1,0,0]},"limit":{"a":0,"b":0,"noLimit":true}}},{"id":11,"parent":18,"joint":"hinge","name":"caster_yoke","parts":[{"id":28,"name":"caster_yoke","children":[]}],"jointData":{"axis":{"origin":[0.25393888603769244,0,0.514514838298887],"direction":[0,1,0]},"limit":{"a":0,"b":0,"noLimit":true}}},{"id":12,"parent":11,"joint":"hinge","name":"wheel","parts":[{"id":29,"name":"wheel","children":[]}],"jointData":{"axis":{"origin":[0,-0.8098479390291516,0.4836433854576705],"direction":[1,0,0]},"limit":{"a":0,"b":0,"noLimit":true}}},{"id":13,"parent":11,"joint":"hinge","name":"wheel","parts":[{"id":30,"name":"wheel","children":[]}],"jointData":{"axis":{"origin":[0,-0.8098479390291516,0.4836433854576705],"direction":[1,0,0]},"limit":{"a":0,"b":0,"noLimit":true}}},{"id":14,"parent":18,"joint":"hinge","name":"caster_yoke","parts":[{"id":25,"name":"caster_yoke","children":[]}],"jointData":{"axis":{"origin":[-0.2480326107549667,0,0.5106440351445807],"direction":[0,1,0]},"limit":{"a":0,"b":0,"noLimit":true}}},{"id":15,"parent":14,"joint":"hinge","name":"wheel","parts":[{"id":26,"name":"wheel","children":[]}],"jointData":{"axis":{"origin":[0,-0.8117528426753511,0.47985379500821157],"direction":[1,0,0]},"limit":{"a":0,"b":0,"noLimit":true}}},{"id":16,"parent":14,"joint":"hinge","name":"wheel","parts":[{"id":27,"name":"wheel","children":[]}],"jointData":{"axis":{"origin":[0,-0.8117528426753511,0.47985379500821157],"direction":[1,0,0]},"limit":{"a":0,"b":0,"noLimit":true}}},{"id":17,"parent":18,"joint":"slider","name":"back_soft_surface","parts":[{"id":54,"name":"back_soft_surface","children":[]},{"id":47,"name":"seat_soft_surface","children":[]},{"id":51,"name":"armrest_soft_surface","children":[]},{"id":52,"name":"arm_holistic_frame","children":[]},{"id":49,"name":"armrest_soft_surface","children":[]},{"id":50,"name":"arm_holistic_frame","children":[]},{"id":43,"name":"central_support","children":[]},{"id":42,"name":"mounting_plate","children":[]}],"jointData":{"axis":{"origin":[0.003092468436697383,0,0.1601520396411574],"direction":[0,-1,0]},"limit":{"a":0,"b":0.1200000000000001,"noLimit":false,"rotates":true,"noRotationLimit":true,"rotationLimit":0}}},{"id":18,"parent":-1,"joint":"free","name":"central_support","parts":[{"id":44,"name":"central_support","children":[]},{"id":45,"name":"central_support","children":[]},{"id":10,"name":"leg","children":[]},{"id":11,"name":"leg","children":[]},{"id":12,"name":"leg","children":[]},{"id":13,"name":"leg","children":[]},{"id":14,"name":"leg","children":[]}],"jointData":{}}]